README.txt
setup.py
src/gocept/__init__.py
src/gocept.munin.egg-info/PKG-INFO
src/gocept.munin.egg-info/SOURCES.txt
src/gocept.munin.egg-info/dependency_links.txt
src/gocept.munin.egg-info/namespace_packages.txt
src/gocept.munin.egg-info/not-zip-safe
src/gocept.munin.egg-info/requires.txt
src/gocept.munin.egg-info/top_level.txt
src/gocept/munin/__init__.py
src/gocept/munin/client.py
