Metadata-Version: 1.0
Name: gocept.munin
Version: 0.1
Summary: Utilities for writing munin plugins.
Home-page: http://www.python.org/pypi/gocept.munin
Author: Christian Theune
Author-email: ct@gocept.com
License: ZPL 2.1
Platform: UNKNOWN
